trig.py
trig-0.1.0.dist-info/LICENSE
trig-0.1.0.dist-info/WHEEL
trig-0.1.0.dist-info/METADATA
trig-0.1.0.dist-info/RECORD
