Metadata-Version: 2.3
Name: trig
Version: 0.1.0
Summary: Trig provides many trigonometric functions.
Author: Tom Fryers
Requires-Python: >=3.7
Classifier: Development Status :: 4 - Beta
Classifier: Programming Language :: Python :: 3
Classifier: License :: OSI Approved :: GNU General Public License v3 or later (GPLv3+)
Classifier: Operating System :: OS Independent
Project-URL: Home, https://gitlab.com/Tom_Fryers/trig
